<?xml version="1.0" encoding="UTF-8"?>
<!DOCTYPE QtCreatorToolChains>
<!-- Written by QtCreator 5.0.0, 2021-11-10T15:09:02. -->
<qtcreator>
 <data>
  <variable>ToolChain.0</variable>
  <valuemap type="QVariantMap">
   <value type="QByteArray" key="ProjectExplorer.ClangToolChain.ParentToolChainId"></value>
   <value type="QString" key="ProjectExplorer.GccToolChain.OriginalTargetTriple">x86_64-apple-darwin20.6.0</value>
   <value type="QString" key="ProjectExplorer.GccToolChain.Path">/usr/bin/clang++</value>
   <valuelist type="QVariantList" key="ProjectExplorer.GccToolChain.PlatformCodeGenFlags"/>
   <valuelist type="QVariantList" key="ProjectExplorer.GccToolChain.PlatformLinkerFlags"/>
   <valuelist type="QVariantList" key="ProjectExplorer.GccToolChain.SupportedAbis">
    <value type="QString">x86-darwin-generic-mach_o-64bit</value>
    <value type="QString">x86-darwin-generic-mach_o-32bit</value>
   </valuelist>
   <value type="QString" key="ProjectExplorer.GccToolChain.TargetAbi">x86-darwin-generic-mach_o-64bit</value>
   <value type="bool" key="ProjectExplorer.ToolChain.Autodetect">true</value>
   <value type="QString" key="ProjectExplorer.ToolChain.DetectionSource"></value>
   <value type="QString" key="ProjectExplorer.ToolChain.DisplayName">Clang (C++, x86 64bit at /usr/bin/clang++)</value>
   <value type="QString" key="ProjectExplorer.ToolChain.Id">ProjectExplorer.ToolChain.Clang:{7f5c8d81-0aec-47f5-9099-3977c062f610}</value>
   <value type="int" key="ProjectExplorer.ToolChain.Language">2</value>
   <value type="QString" key="ProjectExplorer.ToolChain.LanguageV2">Cxx</value>
  </valuemap>
 </data>
 <data>
  <variable>ToolChain.1</variable>
  <valuemap type="QVariantMap">
   <value type="QByteArray" key="ProjectExplorer.ClangToolChain.ParentToolChainId"></value>
   <value type="QString" key="ProjectExplorer.GccToolChain.OriginalTargetTriple">x86_64-apple-darwin20.6.0</value>
   <value type="QString" key="ProjectExplorer.GccToolChain.Path">/usr/bin/clang++</value>
   <valuelist type="QVariantList" key="ProjectExplorer.GccToolChain.PlatformCodeGenFlags"/>
   <valuelist type="QVariantList" key="ProjectExplorer.GccToolChain.PlatformLinkerFlags"/>
   <valuelist type="QVariantList" key="ProjectExplorer.GccToolChain.SupportedAbis">
    <value type="QString">x86-darwin-generic-mach_o-64bit</value>
    <value type="QString">x86-darwin-generic-mach_o-32bit</value>
   </valuelist>
   <value type="QString" key="ProjectExplorer.GccToolChain.TargetAbi">x86-darwin-generic-mach_o-32bit</value>
   <value type="bool" key="ProjectExplorer.ToolChain.Autodetect">true</value>
   <value type="QString" key="ProjectExplorer.ToolChain.DetectionSource"></value>
   <value type="QString" key="ProjectExplorer.ToolChain.DisplayName">Clang (C++, x86 32bit at /usr/bin/clang++)</value>
   <value type="QString" key="ProjectExplorer.ToolChain.Id">ProjectExplorer.ToolChain.Clang:{fcc5fbd0-ca50-4630-85b0-54eeefb97f0a}</value>
   <value type="int" key="ProjectExplorer.ToolChain.Language">2</value>
   <value type="QString" key="ProjectExplorer.ToolChain.LanguageV2">Cxx</value>
  </valuemap>
 </data>
 <data>
  <variable>ToolChain.10</variable>
  <valuemap type="QVariantMap">
   <value type="QByteArray" key="ProjectExplorer.ClangToolChain.ParentToolChainId"></value>
   <value type="QString" key="ProjectExplorer.GccToolChain.OriginalTargetTriple">armv7k-apple-darwin20.6.0</value>
   <value type="QString" key="ProjectExplorer.GccToolChain.Path">/Applications/Xcode.app/Contents/Developer/Toolchains/XcodeDefault.xctoolchain/usr/bin/clang</value>
   <valuelist type="QVariantList" key="ProjectExplorer.GccToolChain.PlatformCodeGenFlags">
    <value type="QString">-arch</value>
    <value type="QString">armv7k</value>
   </valuelist>
   <valuelist type="QVariantList" key="ProjectExplorer.GccToolChain.PlatformLinkerFlags">
    <value type="QString">-arch</value>
    <value type="QString">armv7k</value>
   </valuelist>
   <valuelist type="QVariantList" key="ProjectExplorer.GccToolChain.SupportedAbis">
    <value type="QString">arm-darwin-generic-mach_o-32bit</value>
    <value type="QString">arm-darwin-generic-mach_o-64bit</value>
   </valuelist>
   <value type="QString" key="ProjectExplorer.GccToolChain.TargetAbi">arm-darwin-generic-mach_o-32bit</value>
   <value type="bool" key="ProjectExplorer.ToolChain.Autodetect">true</value>
   <value type="QString" key="ProjectExplorer.ToolChain.DetectionSource"></value>
   <value type="QString" key="ProjectExplorer.ToolChain.DisplayName">Apple Clang (armv7k)</value>
   <value type="QString" key="ProjectExplorer.ToolChain.Id">ProjectExplorer.ToolChain.Clang:{d679b63d-d174-4de4-9901-1ebaae8015aa}</value>
   <value type="int" key="ProjectExplorer.ToolChain.Language">1</value>
   <value type="QString" key="ProjectExplorer.ToolChain.LanguageV2">C</value>
  </valuemap>
 </data>
 <data>
  <variable>ToolChain.11</variable>
  <valuemap type="QVariantMap">
   <value type="QByteArray" key="ProjectExplorer.ClangToolChain.ParentToolChainId"></value>
   <value type="QString" key="ProjectExplorer.GccToolChain.OriginalTargetTriple">armv7k-apple-darwin20.6.0</value>
   <value type="QString" key="ProjectExplorer.GccToolChain.Path">/Applications/Xcode.app/Contents/Developer/Toolchains/XcodeDefault.xctoolchain/usr/bin/clang++</value>
   <valuelist type="QVariantList" key="ProjectExplorer.GccToolChain.PlatformCodeGenFlags">
    <value type="QString">-arch</value>
    <value type="QString">armv7k</value>
   </valuelist>
   <valuelist type="QVariantList" key="ProjectExplorer.GccToolChain.PlatformLinkerFlags">
    <value type="QString">-arch</value>
    <value type="QString">armv7k</value>
   </valuelist>
   <valuelist type="QVariantList" key="ProjectExplorer.GccToolChain.SupportedAbis">
    <value type="QString">arm-darwin-generic-mach_o-32bit</value>
    <value type="QString">arm-darwin-generic-mach_o-64bit</value>
   </valuelist>
   <value type="QString" key="ProjectExplorer.GccToolChain.TargetAbi">arm-darwin-generic-mach_o-32bit</value>
   <value type="bool" key="ProjectExplorer.ToolChain.Autodetect">true</value>
   <value type="QString" key="ProjectExplorer.ToolChain.DetectionSource"></value>
   <value type="QString" key="ProjectExplorer.ToolChain.DisplayName">Apple Clang (armv7k)</value>
   <value type="QString" key="ProjectExplorer.ToolChain.Id">ProjectExplorer.ToolChain.Clang:{2e3d9114-25f5-4d61-92d4-4709472e94e7}</value>
   <value type="int" key="ProjectExplorer.ToolChain.Language">2</value>
   <value type="QString" key="ProjectExplorer.ToolChain.LanguageV2">Cxx</value>
  </valuemap>
 </data>
 <data>
  <variable>ToolChain.12</variable>
  <valuemap type="QVariantMap">
   <value type="QByteArray" key="ProjectExplorer.ClangToolChain.ParentToolChainId"></value>
   <value type="QString" key="ProjectExplorer.GccToolChain.OriginalTargetTriple">armv7-apple-darwin20.6.0</value>
   <value type="QString" key="ProjectExplorer.GccToolChain.Path">/Applications/Xcode.app/Contents/Developer/Toolchains/XcodeDefault.xctoolchain/usr/bin/clang</value>
   <valuelist type="QVariantList" key="ProjectExplorer.GccToolChain.PlatformCodeGenFlags">
    <value type="QString">-arch</value>
    <value type="QString">armv7</value>
   </valuelist>
   <valuelist type="QVariantList" key="ProjectExplorer.GccToolChain.PlatformLinkerFlags">
    <value type="QString">-arch</value>
    <value type="QString">armv7</value>
   </valuelist>
   <valuelist type="QVariantList" key="ProjectExplorer.GccToolChain.SupportedAbis">
    <value type="QString">arm-darwin-generic-mach_o-32bit</value>
    <value type="QString">arm-darwin-generic-mach_o-64bit</value>
   </valuelist>
   <value type="QString" key="ProjectExplorer.GccToolChain.TargetAbi">arm-darwin-generic-mach_o-32bit</value>
   <value type="bool" key="ProjectExplorer.ToolChain.Autodetect">true</value>
   <value type="QString" key="ProjectExplorer.ToolChain.DetectionSource"></value>
   <value type="QString" key="ProjectExplorer.ToolChain.DisplayName">Apple Clang (armv7)</value>
   <value type="QString" key="ProjectExplorer.ToolChain.Id">ProjectExplorer.ToolChain.Clang:{19dbc242-f499-4161-8ece-dd773af4cd4e}</value>
   <value type="int" key="ProjectExplorer.ToolChain.Language">1</value>
   <value type="QString" key="ProjectExplorer.ToolChain.LanguageV2">C</value>
  </valuemap>
 </data>
 <data>
  <variable>ToolChain.13</variable>
  <valuemap type="QVariantMap">
   <value type="QByteArray" key="ProjectExplorer.ClangToolChain.ParentToolChainId"></value>
   <value type="QString" key="ProjectExplorer.GccToolChain.OriginalTargetTriple">armv7-apple-darwin20.6.0</value>
   <value type="QString" key="ProjectExplorer.GccToolChain.Path">/Applications/Xcode.app/Contents/Developer/Toolchains/XcodeDefault.xctoolchain/usr/bin/clang++</value>
   <valuelist type="QVariantList" key="ProjectExplorer.GccToolChain.PlatformCodeGenFlags">
    <value type="QString">-arch</value>
    <value type="QString">armv7</value>
   </valuelist>
   <valuelist type="QVariantList" key="ProjectExplorer.GccToolChain.PlatformLinkerFlags">
    <value type="QString">-arch</value>
    <value type="QString">armv7</value>
   </valuelist>
   <valuelist type="QVariantList" key="ProjectExplorer.GccToolChain.SupportedAbis">
    <value type="QString">arm-darwin-generic-mach_o-32bit</value>
    <value type="QString">arm-darwin-generic-mach_o-64bit</value>
   </valuelist>
   <value type="QString" key="ProjectExplorer.GccToolChain.TargetAbi">arm-darwin-generic-mach_o-32bit</value>
   <value type="bool" key="ProjectExplorer.ToolChain.Autodetect">true</value>
   <value type="QString" key="ProjectExplorer.ToolChain.DetectionSource"></value>
   <value type="QString" key="ProjectExplorer.ToolChain.DisplayName">Apple Clang (armv7)</value>
   <value type="QString" key="ProjectExplorer.ToolChain.Id">ProjectExplorer.ToolChain.Clang:{6c64c47c-607f-4dd8-a93b-63b37305dbdb}</value>
   <value type="int" key="ProjectExplorer.ToolChain.Language">2</value>
   <value type="QString" key="ProjectExplorer.ToolChain.LanguageV2">Cxx</value>
  </valuemap>
 </data>
 <data>
  <variable>ToolChain.14</variable>
  <valuemap type="QVariantMap">
   <value type="QByteArray" key="ProjectExplorer.ClangToolChain.ParentToolChainId"></value>
   <value type="QString" key="ProjectExplorer.GccToolChain.OriginalTargetTriple">x86_64-apple-darwin20.6.0</value>
   <value type="QString" key="ProjectExplorer.GccToolChain.Path">/Applications/Xcode.app/Contents/Developer/Toolchains/XcodeDefault.xctoolchain/usr/bin/clang</value>
   <valuelist type="QVariantList" key="ProjectExplorer.GccToolChain.PlatformCodeGenFlags">
    <value type="QString">-arch</value>
    <value type="QString">x86_64</value>
   </valuelist>
   <valuelist type="QVariantList" key="ProjectExplorer.GccToolChain.PlatformLinkerFlags">
    <value type="QString">-arch</value>
    <value type="QString">x86_64</value>
   </valuelist>
   <valuelist type="QVariantList" key="ProjectExplorer.GccToolChain.SupportedAbis">
    <value type="QString">x86-darwin-generic-mach_o-64bit</value>
    <value type="QString">x86-darwin-generic-mach_o-32bit</value>
   </valuelist>
   <value type="QString" key="ProjectExplorer.GccToolChain.TargetAbi">x86-darwin-generic-mach_o-64bit</value>
   <value type="bool" key="ProjectExplorer.ToolChain.Autodetect">true</value>
   <value type="QString" key="ProjectExplorer.ToolChain.DetectionSource"></value>
   <value type="QString" key="ProjectExplorer.ToolChain.DisplayName">Apple Clang (x86_64)</value>
   <value type="QString" key="ProjectExplorer.ToolChain.Id">ProjectExplorer.ToolChain.Clang:{bc8e9643-f926-460c-8ace-82b0f4777187}</value>
   <value type="int" key="ProjectExplorer.ToolChain.Language">1</value>
   <value type="QString" key="ProjectExplorer.ToolChain.LanguageV2">C</value>
  </valuemap>
 </data>
 <data>
  <variable>ToolChain.15</variable>
  <valuemap type="QVariantMap">
   <value type="QByteArray" key="ProjectExplorer.ClangToolChain.ParentToolChainId"></value>
   <value type="QString" key="ProjectExplorer.GccToolChain.OriginalTargetTriple">x86_64-apple-darwin20.6.0</value>
   <value type="QString" key="ProjectExplorer.GccToolChain.Path">/Applications/Xcode.app/Contents/Developer/Toolchains/XcodeDefault.xctoolchain/usr/bin/clang++</value>
   <valuelist type="QVariantList" key="ProjectExplorer.GccToolChain.PlatformCodeGenFlags">
    <value type="QString">-arch</value>
    <value type="QString">x86_64</value>
   </valuelist>
   <valuelist type="QVariantList" key="ProjectExplorer.GccToolChain.PlatformLinkerFlags">
    <value type="QString">-arch</value>
    <value type="QString">x86_64</value>
   </valuelist>
   <valuelist type="QVariantList" key="ProjectExplorer.GccToolChain.SupportedAbis">
    <value type="QString">x86-darwin-generic-mach_o-64bit</value>
    <value type="QString">x86-darwin-generic-mach_o-32bit</value>
   </valuelist>
   <value type="QString" key="ProjectExplorer.GccToolChain.TargetAbi">x86-darwin-generic-mach_o-64bit</value>
   <value type="bool" key="ProjectExplorer.ToolChain.Autodetect">true</value>
   <value type="QString" key="ProjectExplorer.ToolChain.DetectionSource"></value>
   <value type="QString" key="ProjectExplorer.ToolChain.DisplayName">Apple Clang (x86_64)</value>
   <value type="QString" key="ProjectExplorer.ToolChain.Id">ProjectExplorer.ToolChain.Clang:{bbc8a25d-b9b6-4acf-9f89-88ba2f00cf93}</value>
   <value type="int" key="ProjectExplorer.ToolChain.Language">2</value>
   <value type="QString" key="ProjectExplorer.ToolChain.LanguageV2">Cxx</value>
  </valuemap>
 </data>
 <data>
  <variable>ToolChain.2</variable>
  <valuemap type="QVariantMap">
   <value type="QByteArray" key="ProjectExplorer.ClangToolChain.ParentToolChainId"></value>
   <value type="QString" key="ProjectExplorer.GccToolChain.OriginalTargetTriple">x86_64-apple-darwin20.6.0</value>
   <value type="QString" key="ProjectExplorer.GccToolChain.Path">/usr/bin/clang</value>
   <valuelist type="QVariantList" key="ProjectExplorer.GccToolChain.PlatformCodeGenFlags"/>
   <valuelist type="QVariantList" key="ProjectExplorer.GccToolChain.PlatformLinkerFlags"/>
   <valuelist type="QVariantList" key="ProjectExplorer.GccToolChain.SupportedAbis">
    <value type="QString">x86-darwin-generic-mach_o-64bit</value>
    <value type="QString">x86-darwin-generic-mach_o-32bit</value>
   </valuelist>
   <value type="QString" key="ProjectExplorer.GccToolChain.TargetAbi">x86-darwin-generic-mach_o-64bit</value>
   <value type="bool" key="ProjectExplorer.ToolChain.Autodetect">true</value>
   <value type="QString" key="ProjectExplorer.ToolChain.DetectionSource"></value>
   <value type="QString" key="ProjectExplorer.ToolChain.DisplayName">Clang (C, x86 64bit at /usr/bin/clang)</value>
   <value type="QString" key="ProjectExplorer.ToolChain.Id">ProjectExplorer.ToolChain.Clang:{d9d58f66-0fe3-406c-b7eb-4ab7d423c1ba}</value>
   <value type="int" key="ProjectExplorer.ToolChain.Language">1</value>
   <value type="QString" key="ProjectExplorer.ToolChain.LanguageV2">C</value>
  </valuemap>
 </data>
 <data>
  <variable>ToolChain.3</variable>
  <valuemap type="QVariantMap">
   <value type="QByteArray" key="ProjectExplorer.ClangToolChain.ParentToolChainId"></value>
   <value type="QString" key="ProjectExplorer.GccToolChain.OriginalTargetTriple">x86_64-apple-darwin20.6.0</value>
   <value type="QString" key="ProjectExplorer.GccToolChain.Path">/usr/bin/clang</value>
   <valuelist type="QVariantList" key="ProjectExplorer.GccToolChain.PlatformCodeGenFlags"/>
   <valuelist type="QVariantList" key="ProjectExplorer.GccToolChain.PlatformLinkerFlags"/>
   <valuelist type="QVariantList" key="ProjectExplorer.GccToolChain.SupportedAbis">
    <value type="QString">x86-darwin-generic-mach_o-64bit</value>
    <value type="QString">x86-darwin-generic-mach_o-32bit</value>
   </valuelist>
   <value type="QString" key="ProjectExplorer.GccToolChain.TargetAbi">x86-darwin-generic-mach_o-32bit</value>
   <value type="bool" key="ProjectExplorer.ToolChain.Autodetect">true</value>
   <value type="QString" key="ProjectExplorer.ToolChain.DetectionSource"></value>
   <value type="QString" key="ProjectExplorer.ToolChain.DisplayName">Clang (C, x86 32bit at /usr/bin/clang)</value>
   <value type="QString" key="ProjectExplorer.ToolChain.Id">ProjectExplorer.ToolChain.Clang:{77acf90c-d7b2-403a-b8ea-16696b4a6920}</value>
   <value type="int" key="ProjectExplorer.ToolChain.Language">1</value>
   <value type="QString" key="ProjectExplorer.ToolChain.LanguageV2">C</value>
  </valuemap>
 </data>
 <data>
  <variable>ToolChain.4</variable>
  <valuemap type="QVariantMap">
   <value type="QByteArray" key="ProjectExplorer.ClangToolChain.ParentToolChainId"></value>
   <value type="QString" key="ProjectExplorer.GccToolChain.OriginalTargetTriple">x86_64-apple-darwin20.6.0</value>
   <value type="QString" key="ProjectExplorer.GccToolChain.Path">/Applications/Qt Creator.app/Contents/Resources/libexec/clang/bin/clang</value>
   <valuelist type="QVariantList" key="ProjectExplorer.GccToolChain.PlatformCodeGenFlags"/>
   <valuelist type="QVariantList" key="ProjectExplorer.GccToolChain.PlatformLinkerFlags"/>
   <valuelist type="QVariantList" key="ProjectExplorer.GccToolChain.SupportedAbis">
    <value type="QString">x86-darwin-generic-mach_o-64bit</value>
    <value type="QString">x86-darwin-generic-mach_o-32bit</value>
   </valuelist>
   <value type="QString" key="ProjectExplorer.GccToolChain.TargetAbi">x86-darwin-generic-mach_o-64bit</value>
   <value type="bool" key="ProjectExplorer.ToolChain.Autodetect">true</value>
   <value type="QString" key="ProjectExplorer.ToolChain.DetectionSource"></value>
   <value type="QString" key="ProjectExplorer.ToolChain.DisplayName">Clang (C, x86 64bit at /Applications/Qt Creator.app/Contents/Resources/libexec/clang/bin/clang)</value>
   <value type="QString" key="ProjectExplorer.ToolChain.Id">ProjectExplorer.ToolChain.Clang:{3fec6407-8e0a-4b41-ae48-95d10546659a}</value>
   <value type="int" key="ProjectExplorer.ToolChain.Language">1</value>
   <value type="QString" key="ProjectExplorer.ToolChain.LanguageV2">C</value>
  </valuemap>
 </data>
 <data>
  <variable>ToolChain.5</variable>
  <valuemap type="QVariantMap">
   <value type="QByteArray" key="ProjectExplorer.ClangToolChain.ParentToolChainId"></value>
   <value type="QString" key="ProjectExplorer.GccToolChain.OriginalTargetTriple">x86_64-apple-darwin20.6.0</value>
   <value type="QString" key="ProjectExplorer.GccToolChain.Path">/Applications/Qt Creator.app/Contents/Resources/libexec/clang/bin/clang</value>
   <valuelist type="QVariantList" key="ProjectExplorer.GccToolChain.PlatformCodeGenFlags"/>
   <valuelist type="QVariantList" key="ProjectExplorer.GccToolChain.PlatformLinkerFlags"/>
   <valuelist type="QVariantList" key="ProjectExplorer.GccToolChain.SupportedAbis">
    <value type="QString">x86-darwin-generic-mach_o-64bit</value>
    <value type="QString">x86-darwin-generic-mach_o-32bit</value>
   </valuelist>
   <value type="QString" key="ProjectExplorer.GccToolChain.TargetAbi">x86-darwin-generic-mach_o-32bit</value>
   <value type="bool" key="ProjectExplorer.ToolChain.Autodetect">true</value>
   <value type="QString" key="ProjectExplorer.ToolChain.DetectionSource"></value>
   <value type="QString" key="ProjectExplorer.ToolChain.DisplayName">Clang (C, x86 32bit at /Applications/Qt Creator.app/Contents/Resources/libexec/clang/bin/clang)</value>
   <value type="QString" key="ProjectExplorer.ToolChain.Id">ProjectExplorer.ToolChain.Clang:{d24ce032-0c10-408d-9f72-70b145325e14}</value>
   <value type="int" key="ProjectExplorer.ToolChain.Language">1</value>
   <value type="QString" key="ProjectExplorer.ToolChain.LanguageV2">C</value>
  </valuemap>
 </data>
 <data>
  <variable>ToolChain.6</variable>
  <valuemap type="QVariantMap">
   <value type="QByteArray" key="ProjectExplorer.ClangToolChain.ParentToolChainId"></value>
   <value type="QString" key="ProjectExplorer.GccToolChain.OriginalTargetTriple">arm64-apple-darwin20.6.0</value>
   <value type="QString" key="ProjectExplorer.GccToolChain.Path">/Applications/Xcode.app/Contents/Developer/Toolchains/XcodeDefault.xctoolchain/usr/bin/clang</value>
   <valuelist type="QVariantList" key="ProjectExplorer.GccToolChain.PlatformCodeGenFlags">
    <value type="QString">-arch</value>
    <value type="QString">arm64</value>
   </valuelist>
   <valuelist type="QVariantList" key="ProjectExplorer.GccToolChain.PlatformLinkerFlags">
    <value type="QString">-arch</value>
    <value type="QString">arm64</value>
   </valuelist>
   <valuelist type="QVariantList" key="ProjectExplorer.GccToolChain.SupportedAbis">
    <value type="QString">arm-darwin-generic-mach_o-64bit</value>
    <value type="QString">arm-darwin-generic-mach_o-32bit</value>
   </valuelist>
   <value type="QString" key="ProjectExplorer.GccToolChain.TargetAbi">arm-darwin-generic-mach_o-64bit</value>
   <value type="bool" key="ProjectExplorer.ToolChain.Autodetect">true</value>
   <value type="QString" key="ProjectExplorer.ToolChain.DetectionSource"></value>
   <value type="QString" key="ProjectExplorer.ToolChain.DisplayName">Apple Clang (arm64)</value>
   <value type="QString" key="ProjectExplorer.ToolChain.Id">ProjectExplorer.ToolChain.Clang:{0b32588b-b8be-4d31-ba2a-943962cecc9d}</value>
   <value type="int" key="ProjectExplorer.ToolChain.Language">1</value>
   <value type="QString" key="ProjectExplorer.ToolChain.LanguageV2">C</value>
  </valuemap>
 </data>
 <data>
  <variable>ToolChain.7</variable>
  <valuemap type="QVariantMap">
   <value type="QByteArray" key="ProjectExplorer.ClangToolChain.ParentToolChainId"></value>
   <value type="QString" key="ProjectExplorer.GccToolChain.OriginalTargetTriple">arm64-apple-darwin20.6.0</value>
   <value type="QString" key="ProjectExplorer.GccToolChain.Path">/Applications/Xcode.app/Contents/Developer/Toolchains/XcodeDefault.xctoolchain/usr/bin/clang++</value>
   <valuelist type="QVariantList" key="ProjectExplorer.GccToolChain.PlatformCodeGenFlags">
    <value type="QString">-arch</value>
    <value type="QString">arm64</value>
   </valuelist>
   <valuelist type="QVariantList" key="ProjectExplorer.GccToolChain.PlatformLinkerFlags">
    <value type="QString">-arch</value>
    <value type="QString">arm64</value>
   </valuelist>
   <valuelist type="QVariantList" key="ProjectExplorer.GccToolChain.SupportedAbis">
    <value type="QString">arm-darwin-generic-mach_o-64bit</value>
    <value type="QString">arm-darwin-generic-mach_o-32bit</value>
   </valuelist>
   <value type="QString" key="ProjectExplorer.GccToolChain.TargetAbi">arm-darwin-generic-mach_o-64bit</value>
   <value type="bool" key="ProjectExplorer.ToolChain.Autodetect">true</value>
   <value type="QString" key="ProjectExplorer.ToolChain.DetectionSource"></value>
   <value type="QString" key="ProjectExplorer.ToolChain.DisplayName">Apple Clang (arm64)</value>
   <value type="QString" key="ProjectExplorer.ToolChain.Id">ProjectExplorer.ToolChain.Clang:{486a9a63-839d-4cb6-8234-7c76b70c645b}</value>
   <value type="int" key="ProjectExplorer.ToolChain.Language">2</value>
   <value type="QString" key="ProjectExplorer.ToolChain.LanguageV2">Cxx</value>
  </valuemap>
 </data>
 <data>
  <variable>ToolChain.8</variable>
  <valuemap type="QVariantMap">
   <value type="QByteArray" key="ProjectExplorer.ClangToolChain.ParentToolChainId"></value>
   <value type="QString" key="ProjectExplorer.GccToolChain.OriginalTargetTriple">i386-apple-darwin20.6.0</value>
   <value type="QString" key="ProjectExplorer.GccToolChain.Path">/Applications/Xcode.app/Contents/Developer/Toolchains/XcodeDefault.xctoolchain/usr/bin/clang</value>
   <valuelist type="QVariantList" key="ProjectExplorer.GccToolChain.PlatformCodeGenFlags">
    <value type="QString">-arch</value>
    <value type="QString">i386</value>
   </valuelist>
   <valuelist type="QVariantList" key="ProjectExplorer.GccToolChain.PlatformLinkerFlags">
    <value type="QString">-arch</value>
    <value type="QString">i386</value>
   </valuelist>
   <valuelist type="QVariantList" key="ProjectExplorer.GccToolChain.SupportedAbis">
    <value type="QString">x86-darwin-generic-mach_o-32bit</value>
    <value type="QString">x86-darwin-generic-mach_o-64bit</value>
   </valuelist>
   <value type="QString" key="ProjectExplorer.GccToolChain.TargetAbi">x86-darwin-generic-mach_o-32bit</value>
   <value type="bool" key="ProjectExplorer.ToolChain.Autodetect">true</value>
   <value type="QString" key="ProjectExplorer.ToolChain.DetectionSource"></value>
   <value type="QString" key="ProjectExplorer.ToolChain.DisplayName">Apple Clang (i386)</value>
   <value type="QString" key="ProjectExplorer.ToolChain.Id">ProjectExplorer.ToolChain.Clang:{909eafa0-0a5a-40e5-8b8b-f7dae5e16385}</value>
   <value type="int" key="ProjectExplorer.ToolChain.Language">1</value>
   <value type="QString" key="ProjectExplorer.ToolChain.LanguageV2">C</value>
  </valuemap>
 </data>
 <data>
  <variable>ToolChain.9</variable>
  <valuemap type="QVariantMap">
   <value type="QByteArray" key="ProjectExplorer.ClangToolChain.ParentToolChainId"></value>
   <value type="QString" key="ProjectExplorer.GccToolChain.OriginalTargetTriple">i386-apple-darwin20.6.0</value>
   <value type="QString" key="ProjectExplorer.GccToolChain.Path">/Applications/Xcode.app/Contents/Developer/Toolchains/XcodeDefault.xctoolchain/usr/bin/clang++</value>
   <valuelist type="QVariantList" key="ProjectExplorer.GccToolChain.PlatformCodeGenFlags">
    <value type="QString">-arch</value>
    <value type="QString">i386</value>
   </valuelist>
   <valuelist type="QVariantList" key="ProjectExplorer.GccToolChain.PlatformLinkerFlags">
    <value type="QString">-arch</value>
    <value type="QString">i386</value>
   </valuelist>
   <valuelist type="QVariantList" key="ProjectExplorer.GccToolChain.SupportedAbis">
    <value type="QString">x86-darwin-generic-mach_o-32bit</value>
    <value type="QString">x86-darwin-generic-mach_o-64bit</value>
   </valuelist>
   <value type="QString" key="ProjectExplorer.GccToolChain.TargetAbi">x86-darwin-generic-mach_o-32bit</value>
   <value type="bool" key="ProjectExplorer.ToolChain.Autodetect">true</value>
   <value type="QString" key="ProjectExplorer.ToolChain.DetectionSource"></value>
   <value type="QString" key="ProjectExplorer.ToolChain.DisplayName">Apple Clang (i386)</value>
   <value type="QString" key="ProjectExplorer.ToolChain.Id">ProjectExplorer.ToolChain.Clang:{13272429-ec97-4e27-b249-6374674350f5}</value>
   <value type="int" key="ProjectExplorer.ToolChain.Language">2</value>
   <value type="QString" key="ProjectExplorer.ToolChain.LanguageV2">Cxx</value>
  </valuemap>
 </data>
 <data>
  <variable>ToolChain.Count</variable>
  <value type="int">16</value>
 </data>
 <data>
  <variable>Version</variable>
  <value type="int">1</value>
 </data>
</qtcreator>
